odoo9_addon_medical_lab-9.0.1.0.0-py2.7-nspkg.pth
odoo_addons/medical_lab/__openerp__.py
odoo_addons/medical_lab/__init__.py
odoo_addons/medical_lab/README.rst
odoo_addons/medical_lab/security/medical_security.xml
odoo_addons/medical_lab/security/ir.model.access.csv
odoo_addons/medical_lab/models/medical_lab_test_type.py
odoo_addons/medical_lab/models/medical_lab_test_result.py
odoo_addons/medical_lab/models/medical_lab_test_criterion.py
odoo_addons/medical_lab/models/medical_patient.py
odoo_addons/medical_lab/models/medical_lab_patient.py
odoo_addons/medical_lab/models/__init__.py
odoo_addons/medical_lab/models/medical_lab.py
odoo_addons/medical_lab/views/medical_lab.xml
odoo_addons/medical_lab/views/medical_lab_patient.xml
odoo_addons/medical_lab/views/medical_lab_test_type.xml
odoo_addons/medical_lab/views/medical_menu.xml
odoo_addons/medical_lab/views/medical_patient.xml
odoo9_addon_medical_lab-9.0.1.0.0.dist-info/top_level.txt
odoo9_addon_medical_lab-9.0.1.0.0.dist-info/WHEEL
odoo9_addon_medical_lab-9.0.1.0.0.dist-info/RECORD
odoo9_addon_medical_lab-9.0.1.0.0.dist-info/metadata.json
odoo9_addon_medical_lab-9.0.1.0.0.dist-info/DESCRIPTION.rst
odoo9_addon_medical_lab-9.0.1.0.0.dist-info/METADATA
odoo9_addon_medical_lab-9.0.1.0.0.dist-info/namespace_packages.txt
